{
	"animeName": "13_Amethyst Collector",
	"percentageMax": "0.2",
	"totalFrame": "500",
	"width": "164",
	"height": "380",
	"headHeight": "220",
	"arrayFrame": [
		{"prop":"328,600,0,4.67"},
		{"prop":"328,600,0,2.3"},
		{"prop":"492,600,0,1.26"},
		{"prop":"492,600,0,0.77"},
		{"prop":"0,380,0,0.43"},
		{"prop":"0,380,0,0.2"},
		{"prop":"0,380,0,0.065"},
		{"prop":"0,380,0,0"},
		{"prop":"0,380,0,0"},
		{"prop":"0,380,0,0"},
		{"prop":"0,380,0,0"},
		{"prop":"0,380,0,0"},
		{"prop":"0,600,0,0"},
		{"prop":"0,600,0,-0.46"},
		{"prop":"164,600,0,-1.65"},
		{"prop":"164,600,0,-2.6"},
		{"prop":"0,820,0,4.67"},
		{"prop":"0,820,0,2.3"},
		{"prop":"164,820,0,1.26"},
		{"prop":"164,820,0,0.77"},
		{"prop":"164,820,0,0.43"},
		{"prop":"164,820,0,0.2"},
		{"prop":"164,820,0,0.065"},
		{"prop":"328,820,0,4.67"},
		{"prop":"328,820,0,2.3"},
		{"prop":"492,820,0,1.26"},
		{"prop":"492,820,0,0.77"},
		{"prop":"492,820,0,0.43"},
		{"prop":"492,820,0,0.2"},
		{"prop":"492,820,0,0.065"},
		{"prop":"492,820,0,0"},
		{"prop":"492,820,0,0"},
		{"prop":"492,820,0,0"},
		{"prop":"492,820,0,0"},
		{"prop":"492,820,0,0"},
		{"prop":"0,600,0,0"},
		{"prop":"0,600,0,0"},
		{"prop":"164,600,0,0"},
		{"prop":"164,600,0,0"},
		{"prop":"0,1040,0,-4.67"},
		{"prop":"0,1040,0,-2.3"},
		{"prop":"164,1040,0,-1.26"},
		{"prop":"164,1040,0,-0.77"},
		{"prop":"164,1040,0,-0.43"},
		{"prop":"164,1040,0,-0.2"},
		{"prop":"164,1040,0,-0.065"},
		{"prop":"164,1040,0,0"},
		{"prop":"164,1040,0,0"},
		{"prop":"164,1040,0,0"},
		{"prop":"164,1040,0,0"},
		{"prop":"164,1040,0,0"},
		{"prop":"164,1040,0,0"},
		{"prop":"164,1040,0,0"},
		{"prop":"164,1040,0,0"},
		{"prop":"164,1040,0,0"},
		{"prop":"164,1040,0,0"},
		{"prop":"164,1040,0,0"},
		{"prop":"164,1040,0,0"},
		{"prop":"0,600,0,0"},
		{"prop":"0,600,0,-0.46"},
		{"prop":"164,600,0,-1.65"},
		{"prop":"164,600,0,-2.6"},
		{"prop":"328,600,0,4.67"},
		{"prop":"328,600,0,2.3"},
		{"prop":"492,600,0,1.26"},
		{"prop":"492,600,0,0.77"},
		{"prop":"0,380,0,0.43"},
		{"prop":"0,380,0,0.2"},
		{"prop":"0,380,0,0.065"},
		{"prop":"0,380,0,0"},
		{"prop":"0,380,0,0"},
		{"prop":"0,380,0,0"},
		{"prop":"0,380,0,0"},
		{"prop":"0,380,0,0"},
		{"prop":"0,600,0,0"},
		{"prop":"0,600,0,-0.46"},
		{"prop":"164,600,0,-1.65"},
		{"prop":"164,600,0,-2.6"},
		{"prop":"0,820,0,4.67"},
		{"prop":"0,820,0,2.3"},
		{"prop":"164,820,0,1.26"},
		{"prop":"164,820,0,0.77"},
		{"prop":"164,820,0,0.43"},
		{"prop":"164,820,0,0.2"},
		{"prop":"164,820,0,0.065"},
		{"prop":"328,820,0,4.67"},
		{"prop":"328,820,0,2.3"},
		{"prop":"492,820,0,1.26"},
		{"prop":"492,820,0,0.77"},
		{"prop":"492,820,0,0.43"},
		{"prop":"492,820,0,0.2"},
		{"prop":"492,820,0,0.065"},
		{"prop":"492,820,0,0"},
		{"prop":"492,820,0,0"},
		{"prop":"492,820,0,0"},
		{"prop":"492,820,0,0"},
		{"prop":"492,820,0,0"},
		{"prop":"0,600,0,0"},
		{"prop":"0,600,0,-0.46"},
		{"prop":"164,600,0,-1.65"},
		{"prop":"164,600,0,-2.6"},
		{"prop":"0,1040,0,4.67"},
		{"prop":"0,1040,0,2.3"},
		{"prop":"164,1040,0,1.26"},
		{"prop":"164,1040,0,0.77"},
		{"prop":"164,1040,0,0.43"},
		{"prop":"164,1040,0,0.2"},
		{"prop":"164,1040,0,0.065"},
		{"prop":"164,1040,0,0"},
		{"prop":"164,1040,0,0"},
		{"prop":"164,1040,0,0"},
		{"prop":"164,1040,0,0"},
		{"prop":"164,1040,0,0"},
		{"prop":"164,1040,0,0"},
		{"prop":"164,1040,0,0"},
		{"prop":"164,1040,0,0"},
		{"prop":"164,1040,0,0"},
		{"prop":"164,1040,0,0"},
		{"prop":"164,1040,0,0"},
		{"prop":"164,1040,0,0"},
		{"prop":"0,600,0,0"},
		{"prop":"0,600,0,-0.46"},
		{"prop":"164,600,0,-1.65"},
		{"prop":"164,600,0,-2.6"},
		{"prop":"328,600,-4.67,4.67"},
		{"prop":"328,600,-2.3,2.3"},
		{"prop":"492,600,-1.26,1.26"},
		{"prop":"492,600,-0.77,0.77"},
		{"prop":"0,380,-0.43,0.43"},
		{"prop":"0,380,-0.2,0.2"},
		{"prop":"0,380,-0.065,0.065"},
		{"prop":"0,380,0,0"},
		{"prop":"0,380,0,0"},
		{"prop":"0,380,0,0"},
		{"prop":"0,380,0,0"},
		{"prop":"0,380,0,0"},
		{"prop":"0,600,0,0"},
		{"prop":"0,600,0,-0.46"},
		{"prop":"164,600,0,-1.65"},
		{"prop":"164,600,0,-2.6"},
		{"prop":"0,820,4.67,4.67"},
		{"prop":"0,820,2.3,2.3"},
		{"prop":"164,820,1.26,1.26"},
		{"prop":"164,820,0.77,0.77"},
		{"prop":"164,820,0.43,0.43"},
		{"prop":"164,820,0.2,0.2"},
		{"prop":"164,820,0.065,0.065"},
		{"prop":"328,820,-4.67,4.67"},
		{"prop":"328,820,-2.3,2.3"},
		{"prop":"492,820,-1.26,1.26"},
		{"prop":"492,820,-0.77,0.77"},
		{"prop":"492,820,-0.43,0.43"},
		{"prop":"492,820,-0.2,0.2"},
		{"prop":"492,820,-0.065,0.065"},
		{"prop":"492,820,0,0"},
		{"prop":"492,820,0,0"},
		{"prop":"492,820,0,0"},
		{"prop":"492,820,0,0"},
		{"prop":"492,820,0,0"},
		{"prop":"0,600,0,0"},
		{"prop":"0,600,0,0"},
		{"prop":"164,600,0,0"},
		{"prop":"164,600,0,0"},
		{"prop":"0,1040,0,-4.67"},
		{"prop":"0,1040,0,-2.3"},
		{"prop":"164,1040,0,-1.26"},
		{"prop":"164,1040,0,-0.77"},
		{"prop":"164,1040,0,-0.43"},
		{"prop":"164,1040,0,-0.2"},
		{"prop":"164,1040,0,-0.065"},
		{"prop":"164,1040,0,0"},
		{"prop":"164,1040,0,0"},
		{"prop":"164,1040,0,0"},
		{"prop":"164,1040,0,0"},
		{"prop":"164,1040,0,0"},
		{"prop":"164,1040,0,0"},
		{"prop":"164,1040,0,0"},
		{"prop":"164,1040,0,0"},
		{"prop":"164,1040,0,0"},
		{"prop":"164,1040,0,0"},
		{"prop":"164,1040,0,0"},
		{"prop":"164,1040,0,0"},
		{"prop":"0,600,0,0"},
		{"prop":"0,600,0,0"},
		{"prop":"164,600,0,0"},
		{"prop":"164,600,0,0"},
		{"prop":"328,600,0,-4.67"},
		{"prop":"328,600,0,-2.3"},
		{"prop":"492,600,0,-1.26"},
		{"prop":"492,600,0,-0.77"},
		{"prop":"0,380,0,-0.43"},
		{"prop":"0,380,0,-0.2"},
		{"prop":"0,380,0,-0.065"},
		{"prop":"0,380,0,0"},
		{"prop":"0,380,0,0"},
		{"prop":"0,380,0,0"},
		{"prop":"0,380,0,0"},
		{"prop":"0,380,0,0"},
		{"prop":"0,600,0,0"},
		{"prop":"0,600,0,-0.46"},
		{"prop":"164,600,0,-1.65"},
		{"prop":"164,600,0,-2.6"},
		{"prop":"0,820,0,4.67"},
		{"prop":"0,820,0,2.3"},
		{"prop":"164,820,0,1.26"},
		{"prop":"164,820,0,0.77"},
		{"prop":"164,820,0,0.43"},
		{"prop":"164,820,0,0.2"},
		{"prop":"164,820,0,0.065"},
		{"prop":"328,820,0,4.67"},
		{"prop":"328,820,0,2.3"},
		{"prop":"492,820,0,1.26"},
		{"prop":"492,820,0,0.77"},
		{"prop":"492,820,0,0.43"},
		{"prop":"492,820,0,0.2"},
		{"prop":"492,820,0,0.065"},
		{"prop":"492,820,0,0"},
		{"prop":"492,820,0,0"},
		{"prop":"492,820,0,0"},
		{"prop":"492,820,0,0"},
		{"prop":"492,820,0,0"},
		{"prop":"0,600,0,0"},
		{"prop":"0,600,0,0"},
		{"prop":"164,600,0,0"},
		{"prop":"164,600,0,0"},
		{"prop":"0,1040,0,-4.67"},
		{"prop":"0,1040,0,-2.3"},
		{"prop":"164,1040,0,-1.26"},
		{"prop":"164,1040,0,-0.77"},
		{"prop":"164,1040,0,-0.43"},
		{"prop":"164,1040,0,-0.2"},
		{"prop":"164,1040,0,-0.065"},
		{"prop":"164,1040,0,0"},
		{"prop":"164,1040,0,0"},
		{"prop":"164,1040,0,0"},
		{"prop":"164,1040,0,0"},
		{"prop":"164,1040,0,0"},
		{"prop":"164,1040,0,0"},
		{"prop":"164,1040,0,0"},
		{"prop":"164,1040,0,0"},
		{"prop":"164,1040,0,0"},
		{"prop":"164,1040,0,0"},
		{"prop":"164,1040,0,0"},
		{"prop":"164,1040,0,0"},
		{"prop":"164,1040,0,0"},
		{"prop":"164,1040,0,0"},
		{"prop":"0,600,0,0"},
		{"prop":"0,600,0,-0.46"},
		{"prop":"164,600,0,-1.65"},
		{"prop":"164,600,0,-2.6"},
		{"prop":"328,600,0,4.67"},
		{"prop":"328,600,0,2.3"},
		{"prop":"492,600,0,1.26"},
		{"prop":"492,600,0,0.77"},
		{"prop":"0,380,0,0.43"},
		{"prop":"0,380,0,0.2"},
		{"prop":"0,380,0,0.065"},
		{"prop":"0,380,0,0"},
		{"prop":"0,380,0,0"},
		{"prop":"0,380,0,0"},
		{"prop":"0,380,0,0"},
		{"prop":"0,380,0,0"},
		{"prop":"0,600,0,0"},
		{"prop":"0,600,0,-0.46"},
		{"prop":"164,600,0,-1.65"},
		{"prop":"164,600,0,-2.6"},
		{"prop":"0,820,0,4.67"},
		{"prop":"0,820,0,2.3"},
		{"prop":"164,820,0,1.26"},
		{"prop":"164,820,0,0.77"},
		{"prop":"164,820,0,0.43"},
		{"prop":"164,820,0,0.2"},
		{"prop":"164,820,0,0.065"},
		{"prop":"328,820,0,4.67"},
		{"prop":"328,820,0,2.3"},
		{"prop":"492,820,0,1.26"},
		{"prop":"492,820,0,0.77"},
		{"prop":"492,820,0,0.43"},
		{"prop":"492,820,0,0.2"},
		{"prop":"492,820,0,0.065"},
		{"prop":"492,820,0,0"},
		{"prop":"492,820,0,0"},
		{"prop":"492,820,0,0"},
		{"prop":"492,820,0,0"},
		{"prop":"492,820,0,0"},
		{"prop":"0,600,0,0"},
		{"prop":"0,600,0,0"},
		{"prop":"164,600,0,0"},
		{"prop":"164,600,0,0"},
		{"prop":"328,1040,0,-4.67"},
		{"prop":"328,1040,0,-2.3"},
		{"prop":"492,1040,0,-1.26"},
		{"prop":"492,1040,0,-0.77"},
		{"prop":"492,1040,0,-0.43"},
		{"prop":"492,1040,0,-0.2"},
		{"prop":"492,1040,0,-0.065"},
		{"prop":"492,1040,0,0"},
		{"prop":"492,1040,0,0"},
		{"prop":"492,1040,0,0"},
		{"prop":"492,1040,0,0"},
		{"prop":"492,1040,0,0"},
		{"prop":"492,1040,0,0"},
		{"prop":"492,1040,0,0"},
		{"prop":"492,1040,0,0"},
		{"prop":"492,1040,0,0"},
		{"prop":"492,1040,0,0"},
		{"prop":"492,1040,0,0"},
		{"prop":"492,1040,0,0"},
		{"prop":"0,600,0,0"},
		{"prop":"0,600,0,-0.46"},
		{"prop":"164,600,0,-1.65"},
		{"prop":"164,600,0,-2.6"},
		{"prop":"328,600,0,4.67"},
		{"prop":"328,600,0,2.3"},
		{"prop":"492,600,0,1.26"},
		{"prop":"492,600,0,0.77"},
		{"prop":"0,380,0,0.43"},
		{"prop":"0,380,0,0.2"},
		{"prop":"0,380,0,0.065"},
		{"prop":"0,380,0,0"},
		{"prop":"0,380,0,0"},
		{"prop":"0,380,0,0"},
		{"prop":"0,380,0,0"},
		{"prop":"0,380,0,0"},
		{"prop":"0,600,0,0"},
		{"prop":"0,600,0,-0.46"},
		{"prop":"164,600,0,-1.65"},
		{"prop":"164,600,0,-2.6"},
		{"prop":"0,820,0,4.67"},
		{"prop":"0,820,0,2.3"},
		{"prop":"164,820,0,1.26"},
		{"prop":"164,820,0,0.77"},
		{"prop":"164,820,0,0.43"},
		{"prop":"164,820,0,0.2"},
		{"prop":"164,820,0,0.065"},
		{"prop":"328,820,0,4.67"},
		{"prop":"328,820,0,2.3"},
		{"prop":"492,820,0,1.26"},
		{"prop":"492,820,0,0.77"},
		{"prop":"492,820,0,0.43"},
		{"prop":"492,820,0,0.2"},
		{"prop":"492,820,0,0.065"},
		{"prop":"492,820,0,0"},
		{"prop":"492,820,0,0"},
		{"prop":"492,820,0,0"},
		{"prop":"492,820,0,0"},
		{"prop":"492,820,0,0"},
		{"prop":"0,600,0,0"},
		{"prop":"0,600,0,-0.46"},
		{"prop":"164,600,0,-1.65"},
		{"prop":"164,600,0,-2.6"},
		{"prop":"328,1040,0,4.67"},
		{"prop":"328,1040,0,2.3"},
		{"prop":"492,1040,0,1.26"},
		{"prop":"492,1040,0,0.77"},
		{"prop":"492,1040,0,0.43"},
		{"prop":"492,1040,0,0.2"},
		{"prop":"492,1040,0,0.065"},
		{"prop":"492,1040,0,0"},
		{"prop":"492,1040,0,0"},
		{"prop":"492,1040,0,0"},
		{"prop":"492,1040,0,0"},
		{"prop":"492,1040,0,0"},
		{"prop":"492,1040,0,0"},
		{"prop":"492,1040,0,0"},
		{"prop":"492,1040,0,0"},
		{"prop":"492,1040,0,0"},
		{"prop":"492,1040,0,0"},
		{"prop":"492,1040,0,0"},
		{"prop":"492,1040,0,0"},
		{"prop":"0,600,0,0"},
		{"prop":"0,600,0,-0.46"},
		{"prop":"164,600,0,-1.65"},
		{"prop":"164,600,0,-2.6"},
		{"prop":"328,600,-4.67,4.67"},
		{"prop":"328,600,-2.3,2.3"},
		{"prop":"492,600,-1.26,1.26"},
		{"prop":"492,600,-0.77,0.77"},
		{"prop":"0,380,-0.43,0.43"},
		{"prop":"0,380,-0.2,0.2"},
		{"prop":"0,380,-0.065,0.065"},
		{"prop":"0,380,0,0"},
		{"prop":"0,380,0,0"},
		{"prop":"0,380,0,0"},
		{"prop":"0,380,0,0"},
		{"prop":"0,380,0,0"},
		{"prop":"0,600,0,0"},
		{"prop":"0,600,0,-0.46"},
		{"prop":"164,600,0,-1.65"},
		{"prop":"164,600,0,-2.6"},
		{"prop":"0,820,4.67,4.67"},
		{"prop":"0,820,2.3,2.3"},
		{"prop":"164,820,1.26,1.26"},
		{"prop":"164,820,0.77,0.77"},
		{"prop":"164,820,0.43,0.43"},
		{"prop":"164,820,0.2,0.2"},
		{"prop":"164,820,0.065,0.065"},
		{"prop":"328,820,-4.67,4.67"},
		{"prop":"328,820,-2.3,2.3"},
		{"prop":"492,820,-1.26,1.26"},
		{"prop":"492,820,-0.77,0.77"},
		{"prop":"492,820,-0.43,0.43"},
		{"prop":"492,820,-0.2,0.2"},
		{"prop":"492,820,-0.065,0.065"},
		{"prop":"492,820,0,0"},
		{"prop":"492,820,0,0"},
		{"prop":"492,820,0,0"},
		{"prop":"492,820,0,0"},
		{"prop":"492,820,0,0"},
		{"prop":"0,600,0,0"},
		{"prop":"0,600,0,0"},
		{"prop":"164,600,0,0"},
		{"prop":"164,600,0,0"},
		{"prop":"328,1040,0,-4.67"},
		{"prop":"328,1040,0,-2.3"},
		{"prop":"492,1040,0,-1.26"},
		{"prop":"492,1040,0,-0.77"},
		{"prop":"492,1040,0,-0.43"},
		{"prop":"492,1040,0,-0.2"},
		{"prop":"492,1040,0,-0.065"},
		{"prop":"492,1040,0,0"},
		{"prop":"492,1040,0,0"},
		{"prop":"492,1040,0,0"},
		{"prop":"492,1040,0,0"},
		{"prop":"492,1040,0,0"},
		{"prop":"492,1040,0,0"},
		{"prop":"492,1040,0,0"},
		{"prop":"492,1040,0,0"},
		{"prop":"492,1040,0,0"},
		{"prop":"492,1040,0,0"},
		{"prop":"492,1040,0,0"},
		{"prop":"492,1040,0,0"},
		{"prop":"0,600,0,0"},
		{"prop":"0,600,0,0"},
		{"prop":"164,600,0,0"},
		{"prop":"164,600,0,0"},
		{"prop":"328,600,0,-4.67"},
		{"prop":"328,600,0,-2.3"},
		{"prop":"492,600,0,-1.26"},
		{"prop":"492,600,0,-0.77"},
		{"prop":"0,380,0,-0.43"},
		{"prop":"0,380,0,-0.2"},
		{"prop":"0,380,0,-0.065"},
		{"prop":"0,380,0,0"},
		{"prop":"0,380,0,0"},
		{"prop":"0,380,0,0"},
		{"prop":"0,380,0,0"},
		{"prop":"0,380,0,0"},
		{"prop":"0,600,0,0"},
		{"prop":"0,600,0,-0.46"},
		{"prop":"164,600,0,-1.65"},
		{"prop":"164,600,0,-2.6"},
		{"prop":"0,820,0,4.67"},
		{"prop":"0,820,0,2.3"},
		{"prop":"164,820,0,1.26"},
		{"prop":"164,820,0,0.77"},
		{"prop":"164,820,0,0.43"},
		{"prop":"164,820,0,0.2"},
		{"prop":"164,820,0,0.065"},
		{"prop":"328,820,0,4.67"},
		{"prop":"328,820,0,2.3"},
		{"prop":"492,820,0,1.26"},
		{"prop":"492,820,0,0.77"},
		{"prop":"492,820,0,0.43"},
		{"prop":"492,820,0,0.2"},
		{"prop":"492,820,0,0.065"},
		{"prop":"492,820,0,0"},
		{"prop":"492,820,0,0"},
		{"prop":"492,820,0,0"},
		{"prop":"492,820,0,0"},
		{"prop":"492,820,0,0"},
		{"prop":"0,600,0,0"},
		{"prop":"0,600,0,0"},
		{"prop":"164,600,0,0"},
		{"prop":"164,600,0,0"},
		{"prop":"328,1040,0,-4.67"},
		{"prop":"328,1040,0,-2.3"},
		{"prop":"492,1040,0,-1.26"},
		{"prop":"492,1040,0,-0.77"},
		{"prop":"492,1040,0,-0.43"},
		{"prop":"492,1040,0,-0.2"},
		{"prop":"492,1040,0,-0.065"},
		{"prop":"492,1040,0,0"},
		{"prop":"492,1040,0,0"},
		{"prop":"492,1040,0,0"},
		{"prop":"492,1040,0,0"},
		{"prop":"492,1040,0,0"},
		{"prop":"492,1040,0,0"},
		{"prop":"492,1040,0,0"},
		{"prop":"492,1040,0,0"},
		{"prop":"492,1040,0,0"},
		{"prop":"492,1040,0,0"},
		{"prop":"492,1040,0,0"},
		{"prop":"492,1040,0,0"},
		{"prop":"492,1040,0,0"},
		{"prop":"492,1040,0,0"},
		{"prop":"0,600,0,0"},
		{"prop":"0,600,0,-0.46"},
		{"prop":"164,600,0,-1.65"},
		{"prop":"164,600,0,-2.6"}
]
}